{
	"completely_empty": false,
	"image": {
		"height": 1080,
		"scale": 1.0,
		"width": 1920
	},
	"mark": [
		{
			"class_idx": 8,
			"name": "8",
			"points": [
				{
					"int_x": 844,
					"int_y": 540,
					"x": 0.4395182292,
					"y": 0.50000000005
				},
				{
					"int_x": 854,
					"int_y": 540,
					"x": 0.44459635420000004,
					"y": 0.50000000005
				},
				{
					"int_x": 854,
					"int_y": 557,
					"x": 0.44459635420000004,
					"y": 0.5157407407500001
				},
				{
					"int_x": 844,
					"int_y": 557,
					"x": 0.4395182292,
					"y": 0.5157407407500001
				}
			],
			"rect": {
				"h": 0.01574074070000009,
				"int_h": 18,
				"int_w": 11,
				"int_x": 844,
				"int_y": 540,
				"w": 0.005078125000000044,
				"x": 0.4395182292,
				"y": 0.50000000005
			}
		},
		{
			"class_idx": 1,
			"name": "1",
			"points": [
				{
					"int_x": 855,
					"int_y": 540,
					"x": 0.44505208334999996,
					"y": 0.5
				},
				{
					"int_x": 861,
					"int_y": 540,
					"x": 0.44843750005,
					"y": 0.5
				},
				{
					"int_x": 861,
					"int_y": 558,
					"x": 0.44843750005,
					"y": 0.5171296296000001
				},
				{
					"int_x": 855,
					"int_y": 558,
					"x": 0.44505208334999996,
					"y": 0.5171296296000001
				}
			],
			"rect": {
				"h": 0.017129629600000085,
				"int_h": 19,
				"int_w": 7,
				"int_x": 855,
				"int_y": 540,
				"w": 0.0033854167000000324,
				"x": 0.44505208334999996,
				"y": 0.5
			}
		},
		{
			"class_idx": 10,
			"name": "0",
			"points": [
				{
					"int_x": 861,
					"int_y": 540,
					"x": 0.44843750005,
					"y": 0.5
				},
				{
					"int_x": 873,
					"int_y": 540,
					"x": 0.45442708335,
					"y": 0.5
				},
				{
					"int_x": 873,
					"int_y": 558,
					"x": 0.45442708335,
					"y": 0.5171296296000001
				},
				{
					"int_x": 861,
					"int_y": 558,
					"x": 0.44843750005,
					"y": 0.5171296296000001
				}
			],
			"rect": {
				"h": 0.017129629600000085,
				"int_h": 19,
				"int_w": 13,
				"int_x": 861,
				"int_y": 540,
				"w": 0.00598958329999999,
				"x": 0.44843750005,
				"y": 0.5
			}
		},
		{
			"class_idx": 28,
			"name": "R",
			"points": [
				{
					"int_x": 880,
					"int_y": 539,
					"x": 0.45813802085,
					"y": 0.49942129635
				},
				{
					"int_x": 890,
					"int_y": 539,
					"x": 0.46347656255,
					"y": 0.49942129635
				},
				{
					"int_x": 890,
					"int_y": 558,
					"x": 0.46347656255,
					"y": 0.51678240745
				},
				{
					"int_x": 880,
					"int_y": 558,
					"x": 0.45813802085,
					"y": 0.51678240745
				}
			],
			"rect": {
				"h": 0.01736111110000005,
				"int_h": 20,
				"int_w": 11,
				"int_x": 880,
				"int_y": 539,
				"w": 0.005338541700000032,
				"x": 0.45813802085,
				"y": 0.49942129635
			}
		},
		{
			"class_idx": 29,
			"name": "S",
			"points": [
				{
					"int_x": 890,
					"int_y": 540,
					"x": 0.46328125005,
					"y": 0.5002314814500001
				},
				{
					"int_x": 900,
					"int_y": 540,
					"x": 0.46848958335,
					"y": 0.5002314814500001
				},
				{
					"int_x": 900,
					"int_y": 558,
					"x": 0.46848958335,
					"y": 0.51689814815
				},
				{
					"int_x": 890,
					"int_y": 558,
					"x": 0.46328125005,
					"y": 0.51689814815
				}
			],
			"rect": {
				"h": 0.016666666699999944,
				"int_h": 19,
				"int_w": 11,
				"int_x": 890,
				"int_y": 540,
				"w": 0.005208333300000034,
				"x": 0.46328125005,
				"y": 0.5002314814500001
			}
		},
		{
			"class_idx": 14,
			"name": "D",
			"points": [
				{
					"int_x": 899,
					"int_y": 541,
					"x": 0.46803385415000004,
					"y": 0.50069444445
				},
				{
					"int_x": 908,
					"int_y": 541,
					"x": 0.47285156245,
					"y": 0.50069444445
				},
				{
					"int_x": 908,
					"int_y": 559,
					"x": 0.47285156245,
					"y": 0.5173611111499999
				},
				{
					"int_x": 899,
					"int_y": 559,
					"x": 0.46803385415000004,
					"y": 0.5173611111499999
				}
			],
			"rect": {
				"h": 0.016666666699999944,
				"int_h": 19,
				"int_w": 10,
				"int_x": 899,
				"int_y": 541,
				"w": 0.004817708299999945,
				"x": 0.46803385415000004,
				"y": 0.50069444445
			}
		},
		{
			"class_idx": 0,
			"name": "plate",
			"points": [
				{
					"int_x": 843,
					"int_y": 534,
					"x": 0.43919270835,
					"y": 0.49490740740000005
				},
				{
					"int_x": 909,
					"int_y": 534,
					"x": 0.47330729164999996,
					"y": 0.49490740740000005
				},
				{
					"int_x": 909,
					"int_y": 567,
					"x": 0.47330729164999996,
					"y": 0.525
				},
				{
					"int_x": 843,
					"int_y": 567,
					"x": 0.43919270835,
					"y": 0.525
				}
			],
			"rect": {
				"h": 0.030092592599999968,
				"int_h": 34,
				"int_w": 67,
				"int_x": 843,
				"int_y": 534,
				"w": 0.034114583299999945,
				"x": 0.43919270835,
				"y": 0.49490740740000005
			}
		}
	],
	"timestamp": 1722373978,
	"version": "1.8.27-1"
}
