{
	"completely_empty": false,
	"image": {
		"height": 1080,
		"scale": 1.0,
		"width": 1920
	},
	"mark": [
		{
			"class_idx": 18,
			"name": "H",
			"points": [
				{
					"int_x": 342,
					"int_y": 386,
					"x": 0.1781770833,
					"y": 0.35768518515000003
				},
				{
					"int_x": 369,
					"int_y": 386,
					"x": 0.1922395833,
					"y": 0.35768518515000003
				},
				{
					"int_x": 369,
					"int_y": 428,
					"x": 0.1922395833,
					"y": 0.39638888885
				},
				{
					"int_x": 342,
					"int_y": 428,
					"x": 0.1781770833,
					"y": 0.39638888885
				}
			],
			"rect": {
				"h": 0.03870370369999998,
				"int_h": 43,
				"int_w": 28,
				"int_x": 342,
				"int_y": 386,
				"w": 0.014062499999999978,
				"x": 0.1781770833,
				"y": 0.35768518515000003
			}
		},
		{
			"class_idx": 26,
			"name": "P",
			"points": [
				{
					"int_x": 367,
					"int_y": 387,
					"x": 0.19135416665,
					"y": 0.35824074075
				},
				{
					"int_x": 393,
					"int_y": 387,
					"x": 0.20489583335,
					"y": 0.35824074075
				},
				{
					"int_x": 393,
					"int_y": 428,
					"x": 0.20489583335,
					"y": 0.39657407405
				},
				{
					"int_x": 367,
					"int_y": 428,
					"x": 0.19135416665,
					"y": 0.39657407405
				}
			],
			"rect": {
				"h": 0.038333333299999994,
				"int_h": 42,
				"int_w": 27,
				"int_x": 367,
				"int_y": 387,
				"w": 0.01354166670000001,
				"x": 0.19135416665,
				"y": 0.35824074075
			}
		},
		{
			"class_idx": 6,
			"name": "6",
			"points": [
				{
					"int_x": 392,
					"int_y": 386,
					"x": 0.20437499995,
					"y": 0.35749999995000004
				},
				{
					"int_x": 418,
					"int_y": 386,
					"x": 0.21791666665,
					"y": 0.35749999995000004
				},
				{
					"int_x": 418,
					"int_y": 431,
					"x": 0.21791666665,
					"y": 0.39879629625
				},
				{
					"int_x": 392,
					"int_y": 431,
					"x": 0.20437499995,
					"y": 0.39879629625
				}
			],
			"rect": {
				"h": 0.04129629629999998,
				"int_h": 46,
				"int_w": 27,
				"int_x": 392,
				"int_y": 386,
				"w": 0.01354166670000001,
				"x": 0.20437499995,
				"y": 0.35749999995000004
			}
		},
		{
			"class_idx": 0,
			"name": "plate",
			"points": [
				{
					"int_x": 342,
					"int_y": 369,
					"x": 0.17807291665,
					"y": 0.34212962960000004
				},
				{
					"int_x": 520,
					"int_y": 369,
					"x": 0.27109374995,
					"y": 0.34212962960000004
				},
				{
					"int_x": 520,
					"int_y": 456,
					"x": 0.27109374995,
					"y": 0.4219444444
				},
				{
					"int_x": 342,
					"int_y": 456,
					"x": 0.17807291665,
					"y": 0.4219444444
				}
			],
			"rect": {
				"h": 0.07981481479999997,
				"int_h": 88,
				"int_w": 179,
				"int_x": 342,
				"int_y": 369,
				"w": 0.09302083330000002,
				"x": 0.17807291665,
				"y": 0.34212962960000004
			}
		},
		{
			"class_idx": 4,
			"name": "4",
			"points": [
				{
					"int_x": 443,
					"int_y": 389,
					"x": 0.23083333335,
					"y": 0.35990740740000005
				},
				{
					"int_x": 467,
					"int_y": 389,
					"x": 0.24312500004999998,
					"y": 0.35990740740000005
				},
				{
					"int_x": 467,
					"int_y": 434,
					"x": 0.24312500004999998,
					"y": 0.4019444444
				},
				{
					"int_x": 443,
					"int_y": 434,
					"x": 0.23083333335,
					"y": 0.4019444444
				}
			],
			"rect": {
				"h": 0.042037036999999944,
				"int_h": 46,
				"int_w": 25,
				"int_x": 443,
				"int_y": 389,
				"w": 0.012291666699999981,
				"x": 0.23083333335,
				"y": 0.35990740740000005
			}
		},
		{
			"class_idx": 9,
			"name": "9",
			"points": [
				{
					"int_x": 466,
					"int_y": 390,
					"x": 0.24276041664999998,
					"y": 0.3609259259
				},
				{
					"int_x": 492,
					"int_y": 390,
					"x": 0.25640624995,
					"y": 0.3609259259
				},
				{
					"int_x": 492,
					"int_y": 433,
					"x": 0.25640624995,
					"y": 0.40055555550000005
				},
				{
					"int_x": 466,
					"int_y": 433,
					"x": 0.24276041664999998,
					"y": 0.40055555550000005
				}
			],
			"rect": {
				"h": 0.03962962960000005,
				"int_h": 44,
				"int_w": 27,
				"int_x": 466,
				"int_y": 390,
				"w": 0.013645833300000021,
				"x": 0.24276041664999998,
				"y": 0.3609259259
			}
		},
		{
			"class_idx": 11,
			"name": "A",
			"points": [
				{
					"int_x": 490,
					"int_y": 391,
					"x": 0.2550520833,
					"y": 0.36166666665
				},
				{
					"int_x": 515,
					"int_y": 391,
					"x": 0.2684895833,
					"y": 0.36166666665
				},
				{
					"int_x": 515,
					"int_y": 432,
					"x": 0.2684895833,
					"y": 0.40018518515
				},
				{
					"int_x": 490,
					"int_y": 432,
					"x": 0.2550520833,
					"y": 0.40018518515
				}
			],
			"rect": {
				"h": 0.03851851849999999,
				"int_h": 42,
				"int_w": 26,
				"int_x": 490,
				"int_y": 391,
				"w": 0.013437499999999991,
				"x": 0.2550520833,
				"y": 0.36166666665
			}
		}
	],
	"timestamp": 1722373979,
	"version": "1.8.27-1"
}
