{
	"completely_empty": false,
	"image": {
		"height": 1080,
		"scale": 1.0,
		"width": 1920
	},
	"mark": [
		{
			"class_idx": 16,
			"name": "F",
			"points": [
				{
					"int_x": 1325,
					"int_y": 75,
					"x": 0.6902777778,
					"y": 0.06898148150000001
				},
				{
					"int_x": 1344,
					"int_y": 75,
					"x": 0.7,
					"y": 0.06898148150000001
				},
				{
					"int_x": 1344,
					"int_y": 104,
					"x": 0.7,
					"y": 0.0964506173
				},
				{
					"int_x": 1325,
					"int_y": 104,
					"x": 0.6902777778,
					"y": 0.0964506173
				}
			],
			"rect": {
				"h": 0.02746913579999999,
				"int_h": 30,
				"int_w": 20,
				"int_x": 1325,
				"int_y": 75,
				"w": 0.009722222199999964,
				"x": 0.6902777778,
				"y": 0.06898148150000001
			}
		},
		{
			"class_idx": 0,
			"name": "plate",
			"points": [
				{
					"int_x": 1323,
					"int_y": 69,
					"x": 0.6890624999999999,
					"y": 0.0643518518
				},
				{
					"int_x": 1444,
					"int_y": 69,
					"x": 0.7522569444,
					"y": 0.0643518518
				},
				{
					"int_x": 1444,
					"int_y": 116,
					"x": 0.7522569444,
					"y": 0.1072530864
				},
				{
					"int_x": 1323,
					"int_y": 116,
					"x": 0.6890624999999999,
					"y": 0.1072530864
				}
			],
			"rect": {
				"h": 0.042901234600000004,
				"int_h": 48,
				"int_w": 122,
				"int_x": 1323,
				"int_y": 69,
				"w": 0.0631944444000001,
				"x": 0.6890624999999999,
				"y": 0.0643518518
			}
		},
		{
			"class_idx": 2,
			"name": "2",
			"points": [
				{
					"int_x": 1408,
					"int_y": 73,
					"x": 0.7335069444,
					"y": 0.06805555555000001
				},
				{
					"int_x": 1426,
					"int_y": 73,
					"x": 0.7425347222,
					"y": 0.06805555555000001
				},
				{
					"int_x": 1426,
					"int_y": 105,
					"x": 0.7425347222,
					"y": 0.09737654325
				},
				{
					"int_x": 1408,
					"int_y": 105,
					"x": 0.7335069444,
					"y": 0.09737654325
				}
			],
			"rect": {
				"h": 0.029320987699999995,
				"int_h": 33,
				"int_w": 19,
				"int_x": 1408,
				"int_y": 73,
				"w": 0.00902777780000008,
				"x": 0.7335069444,
				"y": 0.06805555555000001
			}
		},
		{
			"class_idx": 28,
			"name": "R",
			"points": [
				{
					"int_x": 1425,
					"int_y": 74,
					"x": 0.7423611111,
					"y": 0.0686728395
				},
				{
					"int_x": 1443,
					"int_y": 74,
					"x": 0.7517361110999999,
					"y": 0.0686728395
				},
				{
					"int_x": 1443,
					"int_y": 105,
					"x": 0.7517361110999999,
					"y": 0.09675925930000001
				},
				{
					"int_x": 1425,
					"int_y": 105,
					"x": 0.7423611111,
					"y": 0.09675925930000001
				}
			],
			"rect": {
				"h": 0.028086419800000012,
				"int_h": 32,
				"int_w": 19,
				"int_x": 1425,
				"int_y": 74,
				"w": 0.009374999999999911,
				"x": 0.7423611111,
				"y": 0.0686728395
			}
		},
		{
			"class_idx": 7,
			"name": "7",
			"points": [
				{
					"int_x": 1392,
					"int_y": 73,
					"x": 0.725,
					"y": 0.06805555555000001
				},
				{
					"int_x": 1409,
					"int_y": 73,
					"x": 0.7336805556,
					"y": 0.06805555555000001
				},
				{
					"int_x": 1409,
					"int_y": 105,
					"x": 0.7336805556,
					"y": 0.09737654325
				},
				{
					"int_x": 1392,
					"int_y": 105,
					"x": 0.725,
					"y": 0.09737654325
				}
			],
			"rect": {
				"h": 0.029320987699999995,
				"int_h": 33,
				"int_w": 18,
				"int_x": 1392,
				"int_y": 73,
				"w": 0.008680555600000028,
				"x": 0.725,
				"y": 0.06805555555000001
			}
		},
		{
			"class_idx": 20,
			"name": "J",
			"points": [
				{
					"int_x": 1343,
					"int_y": 74,
					"x": 0.6993055555500001,
					"y": 0.06851851855
				},
				{
					"int_x": 1359,
					"int_y": 74,
					"x": 0.70763888885,
					"y": 0.06851851855
				},
				{
					"int_x": 1359,
					"int_y": 105,
					"x": 0.70763888885,
					"y": 0.09691358025
				},
				{
					"int_x": 1343,
					"int_y": 105,
					"x": 0.6993055555500001,
					"y": 0.09691358025
				}
			],
			"rect": {
				"h": 0.0283950617,
				"int_h": 32,
				"int_w": 17,
				"int_x": 1343,
				"int_y": 74,
				"w": 0.008333333299999968,
				"x": 0.6993055555500001,
				"y": 0.06851851855
			}
		},
		{
			"class_idx": 8,
			"name": "8",
			"points": [
				{
					"int_x": 1358,
					"int_y": 75,
					"x": 0.7074218750500001,
					"y": 0.0696759259
				},
				{
					"int_x": 1376,
					"int_y": 75,
					"x": 0.71653645835,
					"y": 0.0696759259
				},
				{
					"int_x": 1376,
					"int_y": 105,
					"x": 0.71653645835,
					"y": 0.09699074070000001
				},
				{
					"int_x": 1358,
					"int_y": 105,
					"x": 0.7074218750500001,
					"y": 0.09699074070000001
				}
			],
			"rect": {
				"h": 0.027314814800000004,
				"int_h": 31,
				"int_w": 19,
				"int_x": 1358,
				"int_y": 75,
				"w": 0.009114583299999923,
				"x": 0.7074218750500001,
				"y": 0.0696759259
			}
		}
	],
	"timestamp": 1722373978,
	"version": "1.8.27-1"
}
