{
	"completely_empty": false,
	"image": {
		"height": 1080,
		"scale": 1.0,
		"width": 1920
	},
	"mark": [
		{
			"class_idx": 8,
			"name": "8",
			"points": [
				{
					"int_x": 1324,
					"int_y": 136,
					"x": 0.68958333695,
					"y": 0.125925919
				},
				{
					"int_x": 1360,
					"int_y": 136,
					"x": 0.7083333376500001,
					"y": 0.125925919
				},
				{
					"int_x": 1360,
					"int_y": 202,
					"x": 0.7083333376500001,
					"y": 0.1870370302
				},
				{
					"int_x": 1324,
					"int_y": 202,
					"x": 0.68958333695,
					"y": 0.1870370302
				}
			],
			"rect": {
				"h": 0.06111111120000001,
				"int_h": 67,
				"int_w": 37,
				"int_x": 1324,
				"int_y": 136,
				"w": 0.018750000700000102,
				"x": 0.68958333695,
				"y": 0.125925919
			}
		},
		{
			"class_idx": 1,
			"name": "1",
			"points": [
				{
					"int_x": 1365,
					"int_y": 135,
					"x": 0.71119791665,
					"y": 0.12530864195
				},
				{
					"int_x": 1383,
					"int_y": 135,
					"x": 0.72039930555,
					"y": 0.12530864195
				},
				{
					"int_x": 1383,
					"int_y": 201,
					"x": 0.72039930555,
					"y": 0.18641975305
				},
				{
					"int_x": 1365,
					"int_y": 201,
					"x": 0.71119791665,
					"y": 0.18641975305
				}
			],
			"rect": {
				"h": 0.061111111100000004,
				"int_h": 67,
				"int_w": 19,
				"int_x": 1365,
				"int_y": 135,
				"w": 0.009201388899999996,
				"x": 0.71119791665,
				"y": 0.12530864195
			}
		},
		{
			"class_idx": 33,
			"name": "W",
			"points": [
				{
					"int_x": 1392,
					"int_y": 138,
					"x": 0.725,
					"y": 0.12762345679999998
				},
				{
					"int_x": 1429,
					"int_y": 138,
					"x": 0.7440972222000001,
					"y": 0.12762345679999998
				},
				{
					"int_x": 1429,
					"int_y": 200,
					"x": 0.7440972222000001,
					"y": 0.1853395062
				},
				{
					"int_x": 1392,
					"int_y": 200,
					"x": 0.725,
					"y": 0.1853395062
				}
			],
			"rect": {
				"h": 0.057716049400000025,
				"int_h": 63,
				"int_w": 38,
				"int_x": 1392,
				"int_y": 138,
				"w": 0.019097222200000097,
				"x": 0.725,
				"y": 0.12762345679999998
			}
		},
		{
			"class_idx": 0,
			"name": "plate",
			"points": [
				{
					"int_x": 1309,
					"int_y": 110,
					"x": 0.6817708334000001,
					"y": 0.10231481479999999
				},
				{
					"int_x": 1430,
					"int_y": 110,
					"x": 0.7449652778,
					"y": 0.10231481479999999
				},
				{
					"int_x": 1430,
					"int_y": 226,
					"x": 0.7449652778,
					"y": 0.2094135802
				},
				{
					"int_x": 1309,
					"int_y": 226,
					"x": 0.6817708334000001,
					"y": 0.2094135802
				}
			],
			"rect": {
				"h": 0.10709876540000002,
				"int_h": 117,
				"int_w": 122,
				"int_x": 1309,
				"int_y": 110,
				"w": 0.06319444439999988,
				"x": 0.6817708334000001,
				"y": 0.10231481479999999
			}
		}
	],
	"timestamp": 1722373976,
	"version": "1.8.27-1"
}
