{
	"completely_empty": false,
	"image": {
		"height": 1080,
		"scale": 1.0,
		"width": 1920
	},
	"mark": [
		{
			"class_idx": 0,
			"name": "plate",
			"points": [
				{
					"int_x": 0,
					"int_y": 539,
					"x": 0.0,
					"y": 0.49946751865000005
				},
				{
					"int_x": 37,
					"int_y": 539,
					"x": 0.0191731576,
					"y": 0.49946751865000005
				},
				{
					"int_x": 37,
					"int_y": 569,
					"x": 0.0191731576,
					"y": 0.52715654955
				},
				{
					"int_x": 0,
					"int_y": 569,
					"x": 0.0,
					"y": 0.52715654955
				}
			],
			"rect": {
				"h": 0.027689030899999967,
				"int_h": 31,
				"int_w": 38,
				"int_x": 0,
				"int_y": 539,
				"w": 0.0191731576,
				"x": 0.0,
				"y": 0.49946751865000005
			}
		},
		{
			"class_idx": 0,
			"name": "plate",
			"points": [
				{
					"int_x": 1665,
					"int_y": 596,
					"x": 0.8670138889,
					"y": 0.5516975308500001
				},
				{
					"int_x": 1719,
					"int_y": 596,
					"x": 0.8954861111,
					"y": 0.5516975308500001
				},
				{
					"int_x": 1719,
					"int_y": 627,
					"x": 0.8954861111,
					"y": 0.58040123455
				},
				{
					"int_x": 1665,
					"int_y": 627,
					"x": 0.8670138889,
					"y": 0.58040123455
				}
			],
			"rect": {
				"h": 0.028703703699999972,
				"int_h": 32,
				"int_w": 55,
				"int_x": 1665,
				"int_y": 596,
				"w": 0.028472222200000008,
				"x": 0.8670138889,
				"y": 0.5516975308500001
			}
		}
	],
	"timestamp": 1722373969,
	"version": "1.8.27-1"
}
