{
	"completely_empty": false,
	"image": {
		"height": 1080,
		"scale": 1.0,
		"width": 1920
	},
	"mark": [
		{
			"class_idx": 0,
			"name": "plate",
			"points": [
				{
					"int_x": 714,
					"int_y": 342,
					"x": 0.371875,
					"y": 0.31701388890000004
				},
				{
					"int_x": 755,
					"int_y": 342,
					"x": 0.39296875000000003,
					"y": 0.31701388890000004
				},
				{
					"int_x": 755,
					"int_y": 363,
					"x": 0.39296875000000003,
					"y": 0.3362268519
				},
				{
					"int_x": 714,
					"int_y": 363,
					"x": 0.371875,
					"y": 0.3362268519
				}
			],
			"rect": {
				"h": 0.019212962999999972,
				"int_h": 22,
				"int_w": 42,
				"int_x": 714,
				"int_y": 342,
				"w": 0.021093750000000022,
				"x": 0.371875,
				"y": 0.31701388890000004
			}
		},
		{
			"class_idx": 18,
			"name": "H",
			"points": [
				{
					"int_x": 1068,
					"int_y": 409,
					"x": 0.5561848958,
					"y": 0.3784722222
				},
				{
					"int_x": 1085,
					"int_y": 409,
					"x": 0.5651692708,
					"y": 0.3784722222
				},
				{
					"int_x": 1085,
					"int_y": 438,
					"x": 0.5651692708,
					"y": 0.40578703699999996
				},
				{
					"int_x": 1068,
					"int_y": 438,
					"x": 0.5561848958,
					"y": 0.40578703699999996
				}
			],
			"rect": {
				"h": 0.027314814799999976,
				"int_h": 30,
				"int_w": 18,
				"int_x": 1068,
				"int_y": 409,
				"w": 0.008984375000000044,
				"x": 0.5561848958,
				"y": 0.3784722222
			}
		},
		{
			"class_idx": 0,
			"name": "plate",
			"points": [
				{
					"int_x": 1061,
					"int_y": 401,
					"x": 0.5524266028,
					"y": 0.3716719915
				},
				{
					"int_x": 1185,
					"int_y": 401,
					"x": 0.6171360096,
					"y": 0.3716719915
				},
				{
					"int_x": 1185,
					"int_y": 454,
					"x": 0.6171360096,
					"y": 0.4206602769
				},
				{
					"int_x": 1061,
					"int_y": 454,
					"x": 0.5524266028,
					"y": 0.4206602769
				}
			],
			"rect": {
				"h": 0.0489882854,
				"int_h": 54,
				"int_w": 125,
				"int_x": 1061,
				"int_y": 401,
				"w": 0.06470940680000004,
				"x": 0.5524266028,
				"y": 0.3716719915
			}
		},
		{
			"class_idx": 35,
			"name": "Y",
			"points": [
				{
					"int_x": 1085,
					"int_y": 409,
					"x": 0.5650390624499999,
					"y": 0.3785879629
				},
				{
					"int_x": 1101,
					"int_y": 409,
					"x": 0.57350260415,
					"y": 0.3785879629
				},
				{
					"int_x": 1101,
					"int_y": 438,
					"x": 0.57350260415,
					"y": 0.4052083333
				},
				{
					"int_x": 1085,
					"int_y": 438,
					"x": 0.5650390624499999,
					"y": 0.4052083333
				}
			],
			"rect": {
				"h": 0.026620370399999982,
				"int_h": 30,
				"int_w": 17,
				"int_x": 1085,
				"int_y": 409,
				"w": 0.008463541700000077,
				"x": 0.5650390624499999,
				"y": 0.3785879629
			}
		},
		{
			"class_idx": 1,
			"name": "1",
			"points": [
				{
					"int_x": 1116,
					"int_y": 409,
					"x": 0.58144531255,
					"y": 0.37905092595
				},
				{
					"int_x": 1127,
					"int_y": 409,
					"x": 0.58704427085,
					"y": 0.37905092595
				},
				{
					"int_x": 1127,
					"int_y": 440,
					"x": 0.58704427085,
					"y": 0.40706018525
				},
				{
					"int_x": 1116,
					"int_y": 440,
					"x": 0.58144531255,
					"y": 0.40706018525
				}
			],
			"rect": {
				"h": 0.028009259299999978,
				"int_h": 32,
				"int_w": 12,
				"int_x": 1116,
				"int_y": 409,
				"w": 0.005598958300000012,
				"x": 0.58144531255,
				"y": 0.37905092595
			}
		},
		{
			"class_idx": 10,
			"name": "0",
			"points": [
				{
					"int_x": 1160,
					"int_y": 413,
					"x": 0.60403645835,
					"y": 0.38252314815
				},
				{
					"int_x": 1175,
					"int_y": 413,
					"x": 0.61210937505,
					"y": 0.38252314815
				},
				{
					"int_x": 1175,
					"int_y": 440,
					"x": 0.61210937505,
					"y": 0.40775462965
				},
				{
					"int_x": 1160,
					"int_y": 440,
					"x": 0.60403645835,
					"y": 0.40775462965
				}
			],
			"rect": {
				"h": 0.025231481499999986,
				"int_h": 28,
				"int_w": 16,
				"int_x": 1160,
				"int_y": 413,
				"w": 0.008072916699999988,
				"x": 0.60403645835,
				"y": 0.38252314815
			}
		},
		{
			"class_idx": 8,
			"name": "8",
			"points": [
				{
					"int_x": 1130,
					"int_y": 411,
					"x": 0.58828125005,
					"y": 0.38032407405
				},
				{
					"int_x": 1146,
					"int_y": 411,
					"x": 0.59661458335,
					"y": 0.38032407405
				},
				{
					"int_x": 1146,
					"int_y": 440,
					"x": 0.59661458335,
					"y": 0.40717592594999996
				},
				{
					"int_x": 1130,
					"int_y": 440,
					"x": 0.58828125005,
					"y": 0.40717592594999996
				}
			],
			"rect": {
				"h": 0.026851851899999946,
				"int_h": 30,
				"int_w": 17,
				"int_x": 1130,
				"int_y": 411,
				"w": 0.008333333299999968,
				"x": 0.58828125005,
				"y": 0.38032407405
			}
		},
		{
			"class_idx": 8,
			"name": "8",
			"points": [
				{
					"int_x": 1146,
					"int_y": 412,
					"x": 0.5967447916499999,
					"y": 0.3818287037
				},
				{
					"int_x": 1160,
					"int_y": 412,
					"x": 0.60429687495,
					"y": 0.3818287037
				},
				{
					"int_x": 1160,
					"int_y": 440,
					"x": 0.60429687495,
					"y": 0.4075231481
				},
				{
					"int_x": 1146,
					"int_y": 440,
					"x": 0.5967447916499999,
					"y": 0.4075231481
				}
			],
			"rect": {
				"h": 0.025694444400000016,
				"int_h": 29,
				"int_w": 15,
				"int_x": 1146,
				"int_y": 412,
				"w": 0.007552083300000012,
				"x": 0.5967447916499999,
				"y": 0.3818287037
			}
		}
	],
	"timestamp": 1722373970,
	"version": "1.8.27-1"
}
