{
	"completely_empty": false,
	"image": {
		"height": 1080,
		"scale": 1.0,
		"width": 1920
	},
	"mark": [
		{
			"class_idx": 0,
			"name": "plate",
			"points": [
				{
					"int_x": 0,
					"int_y": 260,
					"x": 0.0,
					"y": 0.24074074080000002
				},
				{
					"int_x": 68,
					"int_y": 260,
					"x": 0.0354817708,
					"y": 0.24074074080000002
				},
				{
					"int_x": 68,
					"int_y": 298,
					"x": 0.0354817708,
					"y": 0.275462963
				},
				{
					"int_x": 0,
					"int_y": 298,
					"x": 0.0,
					"y": 0.275462963
				}
			],
			"rect": {
				"h": 0.034722222199999986,
				"int_h": 39,
				"int_w": 69,
				"int_x": 0,
				"int_y": 260,
				"w": 0.0354817708,
				"x": 0.0,
				"y": 0.24074074080000002
			}
		}
	],
	"timestamp": 1722373971,
	"version": "1.8.27-1"
}
