{
	"completely_empty": false,
	"image": {
		"height": 1080,
		"scale": 1.0,
		"width": 1920
	},
	"mark": [
		{
			"class_idx": 16,
			"name": "F",
			"points": [
				{
					"int_x": 1471,
					"int_y": 600,
					"x": 0.7661458333000001,
					"y": 0.555462963
				},
				{
					"int_x": 1489,
					"int_y": 600,
					"x": 0.7755208333,
					"y": 0.555462963
				},
				{
					"int_x": 1489,
					"int_y": 635,
					"x": 0.7755208333,
					"y": 0.5882407408
				},
				{
					"int_x": 1471,
					"int_y": 635,
					"x": 0.7661458333000001,
					"y": 0.5882407408
				}
			],
			"rect": {
				"h": 0.03277777780000002,
				"int_h": 36,
				"int_w": 19,
				"int_x": 1471,
				"int_y": 600,
				"w": 0.009374999999999911,
				"x": 0.7661458333000001,
				"y": 0.555462963
			}
		},
		{
			"class_idx": 26,
			"name": "P",
			"points": [
				{
					"int_x": 1489,
					"int_y": 600,
					"x": 0.775625,
					"y": 0.555462963
				},
				{
					"int_x": 1508,
					"int_y": 600,
					"x": 0.785625,
					"y": 0.555462963
				},
				{
					"int_x": 1508,
					"int_y": 635,
					"x": 0.785625,
					"y": 0.5875
				},
				{
					"int_x": 1489,
					"int_y": 635,
					"x": 0.775625,
					"y": 0.5875
				}
			],
			"rect": {
				"h": 0.032037037000000046,
				"int_h": 36,
				"int_w": 20,
				"int_x": 1489,
				"int_y": 600,
				"w": 0.010000000000000009,
				"x": 0.775625,
				"y": 0.555462963
			}
		},
		{
			"class_idx": 5,
			"name": "5",
			"points": [
				{
					"int_x": 1508,
					"int_y": 600,
					"x": 0.7852604167,
					"y": 0.55546296295
				},
				{
					"int_x": 1529,
					"int_y": 600,
					"x": 0.7961979167000001,
					"y": 0.55546296295
				},
				{
					"int_x": 1529,
					"int_y": 633,
					"x": 0.7961979167000001,
					"y": 0.5863888888500001
				},
				{
					"int_x": 1508,
					"int_y": 633,
					"x": 0.7852604167,
					"y": 0.5863888888500001
				}
			],
			"rect": {
				"h": 0.030925925900000095,
				"int_h": 34,
				"int_w": 22,
				"int_x": 1508,
				"int_y": 600,
				"w": 0.010937500000000044,
				"x": 0.7852604167,
				"y": 0.55546296295
			}
		},
		{
			"class_idx": 6,
			"name": "6",
			"points": [
				{
					"int_x": 1548,
					"int_y": 599,
					"x": 0.80604166665,
					"y": 0.5543518519
				},
				{
					"int_x": 1568,
					"int_y": 599,
					"x": 0.8164583333500001,
					"y": 0.5543518519
				},
				{
					"int_x": 1568,
					"int_y": 633,
					"x": 0.8164583333500001,
					"y": 0.5863888889000001
				},
				{
					"int_x": 1548,
					"int_y": 633,
					"x": 0.80604166665,
					"y": 0.5863888889000001
				}
			],
			"rect": {
				"h": 0.032037037000000046,
				"int_h": 35,
				"int_w": 21,
				"int_x": 1548,
				"int_y": 599,
				"w": 0.010416666700000077,
				"x": 0.80604166665,
				"y": 0.5543518519
			}
		},
		{
			"class_idx": 5,
			"name": "5",
			"points": [
				{
					"int_x": 1566,
					"int_y": 599,
					"x": 0.8157291666500001,
					"y": 0.55472222225
				},
				{
					"int_x": 1587,
					"int_y": 599,
					"x": 0.82656249995,
					"y": 0.55472222225
				},
				{
					"int_x": 1587,
					"int_y": 633,
					"x": 0.82656249995,
					"y": 0.5860185185500001
				},
				{
					"int_x": 1566,
					"int_y": 633,
					"x": 0.8157291666500001,
					"y": 0.5860185185500001
				}
			],
			"rect": {
				"h": 0.03129629630000008,
				"int_h": 35,
				"int_w": 22,
				"int_x": 1566,
				"int_y": 599,
				"w": 0.010833333299999914,
				"x": 0.8157291666500001,
				"y": 0.55472222225
			}
		},
		{
			"class_idx": 33,
			"name": "W",
			"points": [
				{
					"int_x": 1586,
					"int_y": 599,
					"x": 0.8259895833,
					"y": 0.55472222225
				},
				{
					"int_x": 1606,
					"int_y": 599,
					"x": 0.8363020833,
					"y": 0.55472222225
				},
				{
					"int_x": 1606,
					"int_y": 633,
					"x": 0.8363020833,
					"y": 0.5856481481500001
				},
				{
					"int_x": 1586,
					"int_y": 633,
					"x": 0.8259895833,
					"y": 0.5856481481500001
				}
			],
			"rect": {
				"h": 0.030925925900000095,
				"int_h": 35,
				"int_w": 21,
				"int_x": 1586,
				"int_y": 599,
				"w": 0.010312499999999947,
				"x": 0.8259895833,
				"y": 0.55472222225
			}
		},
		{
			"class_idx": 0,
			"name": "plate",
			"points": [
				{
					"int_x": 1468,
					"int_y": 589,
					"x": 0.76484374995,
					"y": 0.54564814815
				},
				{
					"int_x": 1609,
					"int_y": 589,
					"x": 0.83807291665,
					"y": 0.54564814815
				},
				{
					"int_x": 1609,
					"int_y": 650,
					"x": 0.83807291665,
					"y": 0.6017592592500001
				},
				{
					"int_x": 1468,
					"int_y": 650,
					"x": 0.76484374995,
					"y": 0.6017592592500001
				}
			],
			"rect": {
				"h": 0.05611111110000011,
				"int_h": 62,
				"int_w": 142,
				"int_x": 1468,
				"int_y": 589,
				"w": 0.07322916670000001,
				"x": 0.76484374995,
				"y": 0.54564814815
			}
		}
	],
	"timestamp": 1722373980,
	"version": "1.8.27-1"
}
