{
	"completely_empty": false,
	"image": {
		"height": 1080,
		"scale": 1.0,
		"width": 1920
	},
	"mark": [
		{
			"class_idx": 13,
			"name": "C",
			"points": [
				{
					"int_x": 1070,
					"int_y": 520,
					"x": 0.55734374995,
					"y": 0.48120370375
				},
				{
					"int_x": 1101,
					"int_y": 520,
					"x": 0.57369791665,
					"y": 0.48120370375
				},
				{
					"int_x": 1101,
					"int_y": 578,
					"x": 0.57369791665,
					"y": 0.53472222225
				},
				{
					"int_x": 1070,
					"int_y": 578,
					"x": 0.55734374995,
					"y": 0.53472222225
				}
			],
			"rect": {
				"h": 0.0535185185,
				"int_h": 59,
				"int_w": 32,
				"int_x": 1070,
				"int_y": 520,
				"w": 0.016354166700000006,
				"x": 0.55734374995,
				"y": 0.48120370375
			}
		},
		{
			"class_idx": 2,
			"name": "2",
			"points": [
				{
					"int_x": 1007,
					"int_y": 518,
					"x": 0.52421875005,
					"y": 0.47981481480000004
				},
				{
					"int_x": 1039,
					"int_y": 518,
					"x": 0.54098958335,
					"y": 0.47981481480000004
				},
				{
					"int_x": 1039,
					"int_y": 577,
					"x": 0.54098958335,
					"y": 0.5342592592000001
				},
				{
					"int_x": 1007,
					"int_y": 577,
					"x": 0.52421875005,
					"y": 0.5342592592000001
				}
			],
			"rect": {
				"h": 0.054444444400000014,
				"int_h": 60,
				"int_w": 33,
				"int_x": 1007,
				"int_y": 518,
				"w": 0.016770833300000065,
				"x": 0.52421875005,
				"y": 0.47981481480000004
			}
		},
		{
			"class_idx": 10,
			"name": "0",
			"points": [
				{
					"int_x": 975,
					"int_y": 518,
					"x": 0.50807291665,
					"y": 0.47953703704999995
				},
				{
					"int_x": 1008,
					"int_y": 518,
					"x": 0.5250520833500001,
					"y": 0.47953703704999995
				},
				{
					"int_x": 1008,
					"int_y": 575,
					"x": 0.5250520833500001,
					"y": 0.53268518515
				},
				{
					"int_x": 975,
					"int_y": 575,
					"x": 0.50807291665,
					"y": 0.53268518515
				}
			],
			"rect": {
				"h": 0.053148148100000014,
				"int_h": 58,
				"int_w": 34,
				"int_x": 975,
				"int_y": 518,
				"w": 0.016979166700000103,
				"x": 0.50807291665,
				"y": 0.47953703704999995
			}
		},
		{
			"class_idx": 4,
			"name": "4",
			"points": [
				{
					"int_x": 944,
					"int_y": 516,
					"x": 0.49177083334999994,
					"y": 0.47805555555
				},
				{
					"int_x": 977,
					"int_y": 516,
					"x": 0.50906250005,
					"y": 0.47805555555
				},
				{
					"int_x": 977,
					"int_y": 575,
					"x": 0.50906250005,
					"y": 0.53194444445
				},
				{
					"int_x": 944,
					"int_y": 575,
					"x": 0.49177083334999994,
					"y": 0.53194444445
				}
			],
			"rect": {
				"h": 0.05388888889999999,
				"int_h": 60,
				"int_w": 34,
				"int_x": 944,
				"int_y": 516,
				"w": 0.01729166670000004,
				"x": 0.49177083334999994,
				"y": 0.47805555555
			}
		},
		{
			"class_idx": 0,
			"name": "plate",
			"points": [
				{
					"int_x": 942,
					"int_y": 503,
					"x": 0.49072916665000005,
					"y": 0.46583333335
				},
				{
					"int_x": 1167,
					"int_y": 503,
					"x": 0.6078124999500001,
					"y": 0.46583333335
				},
				{
					"int_x": 1167,
					"int_y": 598,
					"x": 0.6078124999500001,
					"y": 0.55416666665
				},
				{
					"int_x": 942,
					"int_y": 598,
					"x": 0.49072916665000005,
					"y": 0.55416666665
				}
			],
			"rect": {
				"h": 0.08833333330000004,
				"int_h": 96,
				"int_w": 226,
				"int_x": 942,
				"int_y": 503,
				"w": 0.11708333330000004,
				"x": 0.49072916665000005,
				"y": 0.46583333335
			}
		},
		{
			"class_idx": 30,
			"name": "T",
			"points": [
				{
					"int_x": 1132,
					"int_y": 521,
					"x": 0.5896874999999999,
					"y": 0.48268518515000003
				},
				{
					"int_x": 1163,
					"int_y": 521,
					"x": 0.6059375,
					"y": 0.48268518515000003
				},
				{
					"int_x": 1163,
					"int_y": 579,
					"x": 0.6059375,
					"y": 0.53620370365
				},
				{
					"int_x": 1132,
					"int_y": 579,
					"x": 0.5896874999999999,
					"y": 0.53620370365
				}
			],
			"rect": {
				"h": 0.0535185185,
				"int_h": 59,
				"int_w": 32,
				"int_x": 1132,
				"int_y": 521,
				"w": 0.016250000000000098,
				"x": 0.5896874999999999,
				"y": 0.48268518515000003
			}
		},
		{
			"class_idx": 29,
			"name": "S",
			"points": [
				{
					"int_x": 1100,
					"int_y": 520,
					"x": 0.5728124999499999,
					"y": 0.48157407404999997
				},
				{
					"int_x": 1133,
					"int_y": 520,
					"x": 0.59010416665,
					"y": 0.48157407404999997
				},
				{
					"int_x": 1133,
					"int_y": 578,
					"x": 0.59010416665,
					"y": 0.53546296295
				},
				{
					"int_x": 1100,
					"int_y": 578,
					"x": 0.5728124999499999,
					"y": 0.53546296295
				}
			],
			"rect": {
				"h": 0.05388888889999999,
				"int_h": 59,
				"int_w": 34,
				"int_x": 1100,
				"int_y": 520,
				"w": 0.01729166670000004,
				"x": 0.5728124999499999,
				"y": 0.48157407404999997
			}
		}
	],
	"timestamp": 1722373979,
	"version": "1.8.27-1"
}
